bugrest/__init__.py
bugrest/style.css
bugrest-1.1.1.data/scripts/br
bugrest-1.1.1.dist-info/DESCRIPTION.rst
bugrest-1.1.1.dist-info/METADATA
bugrest-1.1.1.dist-info/RECORD
bugrest-1.1.1.dist-info/WHEEL
bugrest-1.1.1.dist-info/metadata.json
bugrest-1.1.1.dist-info/top_level.txt
