Metadata-Version: 2.0
Name: bugrest
Version: 1.1.1
Summary: Awesome minimalist command line ticket/bug tracker based on ReStructuredText
Home-page: https://github.com/fdev31/bugrest
Author: Fabien Devaux
Author-email: fdev31@gmail.com
License: MIT
Platform: UNKNOWN
Classifier: Environment :: Console
Classifier: Development Status :: 4 - Beta
Classifier: Programming Language :: Python :: 2.7
Classifier: Programming Language :: Python :: 3
Classifier: Programming Language :: Python :: 3.1
Classifier: Programming Language :: Python :: 3.2
Classifier: Programming Language :: Python :: 3.3
Classifier: Programming Language :: Python :: 3.4
Requires-Dist: docutils (>=0.12)
